warc_cache/__init__.py
warc_cache/test_dummy.py
warc_cache-1.0.4.dist-info/licenses/LICENSE
warc_cache-1.0.4.dist-info/METADATA
warc_cache-1.0.4.dist-info/WHEEL
warc_cache-1.0.4.dist-info/top_level.txt
warc_cache-1.0.4.dist-info/RECORD
